coinex_mcp_server/__init__.py
coinex_mcp_server/coinex_client.py
coinex_mcp_server/main.py
coinex_mcp_server-0.1.0a8.dist-info/licenses/LICENSE
coinex_mcp_server-0.1.0a8.dist-info/METADATA
coinex_mcp_server-0.1.0a8.dist-info/WHEEL
coinex_mcp_server-0.1.0a8.dist-info/entry_points.txt
coinex_mcp_server-0.1.0a8.dist-info/top_level.txt
coinex_mcp_server-0.1.0a8.dist-info/RECORD
