Metadata-Version: 2.4
Name: coinex-mcp-server
Version: 0.1.0a8
Summary: A CoinEx MCP (Model Context Protocol) server that enables AI agents to interact with the CoinEx cryptocurrency exchange
Author: CoinEx MCP Contributors
Maintainer: CoinEx MCP Contributors
License-Expression: Apache-2.0
Project-URL: Homepage, https://github.com/coinexcom/coinex_mcp_server
Project-URL: Repository, https://github.com/coinexcom/coinex_mcp_server
Project-URL: Documentation, https://github.com/coinexcom/coinex_mcp_server#readme
Project-URL: Bug Tracker, https://github.com/coinexcom/coinex_mcp_server/issues
Keywords: coinex,mcp,model-context-protocol,cryptocurrency,exchange,trading,api,fastmcp,ai-agent
Classifier: Development Status :: 3 - Alpha
Classifier: Intended Audience :: Developers
Classifier: Programming Language :: Python :: 3
Classifier: Programming Language :: Python :: 3.10
Classifier: Programming Language :: Python :: 3.11
Classifier: Programming Language :: Python :: 3.12
Classifier: Topic :: Software Development :: Libraries :: Python Modules
Classifier: Topic :: Office/Business :: Financial
Classifier: Topic :: Internet :: WWW/HTTP :: HTTP Servers
Classifier: Topic :: Scientific/Engineering :: Artificial Intelligence
Classifier: Framework :: AsyncIO
Classifier: Environment :: Console
Requires-Python: >=3.10
License-File: LICENSE
Requires-Dist: httpx>=0.28.1
Requires-Dist: fastmcp==2.12.4
Requires-Dist: python-dotenv>=1.1.1
Requires-Dist: pydantic>=2.7.0
Dynamic: license-file
